pygenstub.py
pygenstub.pyi
pygenstub-2.0.1.dist-info/entry_points.txt
pygenstub-2.0.1.dist-info/LICENSE.txt
pygenstub-2.0.1.dist-info/WHEEL
pygenstub-2.0.1.dist-info/METADATA
pygenstub-2.0.1.dist-info/RECORD
