Metadata-Version: 2.1
Name: pygenstub
Version: 2.0.1
Summary: Python stub file generator.
Home-page: https://tekir.org/pygenstub/
License: GPL-3.0+
Keywords: type hints,stub files,docstring
Author: H. Turgut Uyar
Author-email: uyar@tekir.org
Requires-Python: >=3.6,<4.0
Classifier: Development Status :: 5 - Production/Stable
Classifier: Environment :: Console
Classifier: Framework :: Sphinx :: Extension
Classifier: Intended Audience :: Developers
Classifier: License :: OSI Approved :: GNU General Public License v3 or later (GPLv3+)
Classifier: Operating System :: OS Independent
Classifier: Programming Language :: Python
Classifier: Programming Language :: Python :: 3
Classifier: Programming Language :: Python :: 3.6
Classifier: Programming Language :: Python :: 3.7
Classifier: Programming Language :: Python :: 3.8
Classifier: Programming Language :: Python :: 3.9
Classifier: Topic :: Documentation :: Sphinx
Classifier: Topic :: Software Development :: Documentation
Requires-Dist: docutils (>=0.16,<0.17)
Project-URL: Documentation, https://pygenstub.readthedocs.io/
Project-URL: Repository, https://github.com/uyar/pygenstub
